notifyforeground/__init__.py
notifyforeground/__main__.py
notifyforeground/base.py
notifyforeground/core.py
notifyforeground/styles.py
notifyforeground/sword.py
notifyforeground-1.0.dist-info/METADATA
notifyforeground-1.0.dist-info/WHEEL
notifyforeground-1.0.dist-info/top_level.txt
notifyforeground-1.0.dist-info/RECORD
